SiteScraper/SiteScraper.py
SiteScraper/__init__.py
SiteScraper-0.2.2.dist-info/METADATA
SiteScraper-0.2.2.dist-info/WHEEL
SiteScraper-0.2.2.dist-info/top_level.txt
SiteScraper-0.2.2.dist-info/RECORD
