Metadata-Version: 2.1
Name: SiteScraper
Version: 0.2.2
Summary: Scraping high intensity content sites
Author: Ibrahim
Author-email: string2025@gmail.com
Requires-Dist: selenium
